anova/__init__.py
anova-0.0.2.dist-info/LICENSE
anova-0.0.2.dist-info/METADATA
anova-0.0.2.dist-info/WHEEL
anova-0.0.2.dist-info/top_level.txt
anova-0.0.2.dist-info/RECORD
